ataraxis_time/precision_timer_ext.cpython-313-darwin.so
ataraxis_time/__init__.py
ataraxis_time/py.typed
ataraxis_time/time_helpers/helper_functions.py
ataraxis_time/time_helpers/__init__.py
ataraxis_time/precision_timer/timer_benchmark.py
ataraxis_time/precision_timer/__init__.py
ataraxis_time/precision_timer/timer_class.py
ataraxis_time-5.0.0.dist-info/RECORD
ataraxis_time-5.0.0.dist-info/WHEEL
ataraxis_time-5.0.0.dist-info/entry_points.txt
ataraxis_time-5.0.0.dist-info/METADATA
ataraxis_time-5.0.0.dist-info/licenses/LICENSE
