Metadata-Version: 2.1
Name: ataraxis-time
Version: 5.0.0
Summary: Provides a high-precision thread-safe timer and helper methods to work with date and time data.
Keywords: time,high precision,timer,elapsed,delay,time conversion,non-blocking,blocking,date,ataraxis
Author: Ivan Kondratyev
Maintainer-Email: Ivan Kondratyev <ik278@cornell.edu>
License:                     GNU GENERAL PUBLIC LICENSE
Classifier: Development Status :: 5 - Production/Stable
Classifier: Intended Audience :: Developers
Classifier: Topic :: Software Development
Classifier: License :: OSI Approved :: GNU General Public License v3 or later (GPLv3+)
Classifier: Programming Language :: Python :: 3.12
Classifier: Programming Language :: Python :: 3.13
Classifier: Programming Language :: Python :: 3.14
Classifier: Programming Language :: C++
Classifier: Operating System :: Microsoft :: Windows
Classifier: Operating System :: POSIX :: Linux
Classifier: Operating System :: MacOS :: MacOS X
Classifier: Typing :: Typed
Project-URL: Homepage, https://github.com/Sun-Lab-NBB/ataraxis-time
Project-URL: Documentation, https://ataraxis-time-api-docs.netlify.app/
Requires-Python: <3.15,>=3.12
Requires-Dist: numpy<3,>=2
Requires-Dist: click<9,>=8
Requires-Dist: tqdm<5,>=4
Requires-Dist: ataraxis-base-utilities<6,>=5
Provides-Extra: dev
Requires-Dist: tox<5,>=4; extra == "dev"
Requires-Dist: uv<1,>=0; extra == "dev"
Requires-Dist: tox-uv<2,>=1; extra == "dev"
Requires-Dist: ataraxis-automation<8,>=7; extra == "dev"
Requires-Dist: types-tqdm<5,>=4; extra == "dev"
